llemb/__init__.py
llemb/core.py
llemb/interfaces.py
llemb/backends/__init__.py
llemb/backends/transformers_backend.py
llemb/backends/vllm_backend.py
llemb-0.3.0.dist-info/licenses/LICENSE
llemb-0.3.0.dist-info/METADATA
llemb-0.3.0.dist-info/WHEEL
llemb-0.3.0.dist-info/top_level.txt
llemb-0.3.0.dist-info/RECORD
