Metadata-Version: 2.4
Name: llemb
Version: 0.3.0
Summary: Embedding extractor for decoder-only LLMs
Classifier: Programming Language :: Python :: 3
Classifier: Programming Language :: Python :: 3.9
Classifier: Programming Language :: Python :: 3.10
Classifier: Programming Language :: Python :: 3.11
Classifier: Programming Language :: Python :: 3.12
Classifier: Programming Language :: Python :: 3.13
Requires-Python: >=3.9
License-File: LICENSE
Requires-Dist: accelerate>=1.10.1
Requires-Dist: bitsandbytes>=0.48.2
Requires-Dist: numpy>=2.0.2
Requires-Dist: torch>=2.0.0
Requires-Dist: tqdm>=4.66.0
Requires-Dist: transformers>=4.30.0
Provides-Extra: quantization
Provides-Extra: vllm
Requires-Dist: vllm>=0.10.0; extra == "vllm"
Dynamic: license-file
